huaweicloudsdkdlf/__init__.py
huaweicloudsdkdlf/v1/__init__.py
huaweicloudsdkdlf/v1/dlf_async_client.py
huaweicloudsdkdlf/v1/dlf_client.py
huaweicloudsdkdlf/v1/model/__init__.py
huaweicloudsdkdlf/v1/model/basic_info.py
huaweicloudsdkdlf/v1/model/cancel_script_request.py
huaweicloudsdkdlf/v1/model/cancel_script_response.py
huaweicloudsdkdlf/v1/model/condition.py
huaweicloudsdkdlf/v1/model/connection_info.py
huaweicloudsdkdlf/v1/model/connection_param.py
huaweicloudsdkdlf/v1/model/create_connection_request.py
huaweicloudsdkdlf/v1/model/create_connection_response.py
huaweicloudsdkdlf/v1/model/create_job_request.py
huaweicloudsdkdlf/v1/model/create_job_response.py
huaweicloudsdkdlf/v1/model/create_resource_request.py
huaweicloudsdkdlf/v1/model/create_resource_response.py
huaweicloudsdkdlf/v1/model/create_script_request.py
huaweicloudsdkdlf/v1/model/create_script_response.py
huaweicloudsdkdlf/v1/model/cron.py
huaweicloudsdkdlf/v1/model/delete_connction_request.py
huaweicloudsdkdlf/v1/model/delete_connction_response.py
huaweicloudsdkdlf/v1/model/delete_job_request.py
huaweicloudsdkdlf/v1/model/delete_job_response.py
huaweicloudsdkdlf/v1/model/delete_resource_request.py
huaweicloudsdkdlf/v1/model/delete_resource_response.py
huaweicloudsdkdlf/v1/model/delete_script_request.py
huaweicloudsdkdlf/v1/model/delete_script_response.py
huaweicloudsdkdlf/v1/model/depend_job.py
huaweicloudsdkdlf/v1/model/depend_work_space_job.py
huaweicloudsdkdlf/v1/model/directory_tree_resp.py
huaweicloudsdkdlf/v1/model/event.py
huaweicloudsdkdlf/v1/model/execute_script_req.py
huaweicloudsdkdlf/v1/model/execute_script_request.py
huaweicloudsdkdlf/v1/model/execute_script_response.py
huaweicloudsdkdlf/v1/model/export_connections_request.py
huaweicloudsdkdlf/v1/model/export_connections_response.py
huaweicloudsdkdlf/v1/model/export_job_list_request.py
huaweicloudsdkdlf/v1/model/export_job_list_response.py
huaweicloudsdkdlf/v1/model/export_job_request.py
huaweicloudsdkdlf/v1/model/export_job_response.py
huaweicloudsdkdlf-3.1.184.dist-info/METADATA
huaweicloudsdkdlf-3.1.184.dist-info/WHEEL
huaweicloudsdkdlf-3.1.184.dist-info/licenses/LICENSE
huaweicloudsdkdlf-3.1.184.dist-info/RECORD
